labelme/__init__.py
labelme/__main__.py
labelme/app.py
labelme/imageProcessing.py
labelme/label_file.py
labelme/logger.py
labelme/shape.py
labelme/testing.py
labelme/cli/__init__.py
labelme/cli/draw_json.py
labelme/cli/draw_label_png.py
labelme/cli/json_to_dataset.py
labelme/cli/on_docker.py
labelme/config/__init__.py
labelme/config/default_config.yaml
labelme/icons/cancel.png
labelme/icons/close.png
labelme/icons/color-line.png
labelme/icons/color.png
labelme/icons/copy.png
labelme/icons/delete.png
labelme/icons/done.png
labelme/icons/done.svg
labelme/icons/edit.png
labelme/icons/expert.png
labelme/icons/eye.png
labelme/icons/feBlend-icon.png
labelme/icons/file.png
labelme/icons/fit-width.png
labelme/icons/fit-window.png
labelme/icons/fit.png
labelme/icons/help.png
labelme/icons/icon.icns
labelme/icons/icon.ico
labelme/icons/icon.png
labelme/icons/labels.png
labelme/icons/labels.svg
labelme/icons/new.png
labelme/icons/next.png
labelme/icons/objects.png
labelme/icons/open.png
labelme/icons/open.svg
labelme/icons/prev.png
labelme/icons/quit.png
labelme/icons/save-as.png
labelme/icons/save-as.svg
labelme/icons/save.png
labelme/icons/save.svg
labelme/icons/undo-cross.png
labelme/icons/undo.png
labelme/icons/zoom-in.png
labelme/icons/zoom-out.png
labelme/icons/zoom.png
labelme/utils/__init__.py
labelme/utils/_io.py
labelme/utils/image.py
labelme/utils/qt.py
labelme/utils/shape.py
labelme/widgets/__init__.py
labelme/widgets/brightness_contrast_dialog.py
labelme/widgets/canvas.py
labelme/widgets/color_dialog.py
labelme/widgets/escapable_qlist_widget.py
labelme/widgets/file_dialog_preview.py
labelme/widgets/label_dialog.py
labelme/widgets/label_list_widget.py
labelme/widgets/tool_bar.py
labelme/widgets/unique_label_qlist_widget.py
labelme/widgets/zoom_widget.py
labelmeAMIT-1.0.5.2.8.dist-info/LICENSE
labelmeAMIT-1.0.5.2.8.dist-info/METADATA
labelmeAMIT-1.0.5.2.8.dist-info/WHEEL
labelmeAMIT-1.0.5.2.8.dist-info/entry_points.txt
labelmeAMIT-1.0.5.2.8.dist-info/top_level.txt
labelmeAMIT-1.0.5.2.8.dist-info/RECORD
