Metadata-Version: 2.1
Name: labelmeAMIT
Version: 1.0.5.2.8
Summary: Image Polygonal Annotation with Python
Home-page: https://github.com/wkentaro/labelme
Author: Kentaro Wada
Author-email: www.kentaro.wada@gmail.com
License: GPLv3
Keywords: Image Annotation,Machine Learning
Classifier: Development Status :: 5 - Production/Stable
Classifier: Intended Audience :: Developers
Classifier: Intended Audience :: Science/Research
Classifier: Natural Language :: English
Classifier: Operating System :: OS Independent
Classifier: Programming Language :: Python
Classifier: Programming Language :: Python :: 3.5
Classifier: Programming Language :: Python :: 3.6
Classifier: Programming Language :: Python :: 3.7
Classifier: Programming Language :: Python :: 3.8
Classifier: Programming Language :: Python :: 3.9
Classifier: Programming Language :: Python :: 3 :: Only
License-File: LICENSE
Requires-Dist: imgviz (>=0.11)
Requires-Dist: matplotlib
Requires-Dist: natsort (>=7.1.0)
Requires-Dist: numpy
Requires-Dist: Pillow (>=2.8)
Requires-Dist: PyYAML
Requires-Dist: qtpy (!=1.11.2)
Requires-Dist: termcolor
